batch_normalization_folding/__init__.py
batch_normalization_folding/folder.py
batch_normalization_folding/TensorFlow/__init__.py
batch_normalization_folding/TensorFlow/add_biases.py
batch_normalization_folding/TensorFlow/back_forth.py
batch_normalization_folding/TensorFlow/calculus.py
batch_normalization_folding/TensorFlow/concat_handler.py
batch_normalization_folding/TensorFlow/deep_copy.py
batch_normalization_folding/TensorFlow/graph_modif.py
batch_normalization_folding/TensorFlow/graph_path.py
batch_normalization_folding/TensorFlow/lambda_layers.py
batch_normalization_folding/TensorFlow/modify_bn_graph.py
batch_normalization_folding/TensorFlow/package.py
batch_normalization_folding/TensorFlow/tf_bn_fold.py
batch_normalization_folding/TensorFlow/to_fold_or_not_to_fold.py
batch_normalization_folding/TensorFlow/update_fold_weights.py
batch_normalization_folding/UnitTest/__init__.py
batch_normalization_folding/UnitTest/model_generator.py
batch_normalization_folding/UnitTest/test_a_model.py
tensorflow_batchnorm_folding-1.0.9.dist-info/LICENSE
tensorflow_batchnorm_folding-1.0.9.dist-info/METADATA
tensorflow_batchnorm_folding-1.0.9.dist-info/WHEEL
tensorflow_batchnorm_folding-1.0.9.dist-info/top_level.txt
tensorflow_batchnorm_folding-1.0.9.dist-info/RECORD
