Metadata-Version: 2.1
Name: tensorflow-batchnorm-folding
Version: 1.0.9
Summary: Folds BN layers in tf keras models.
Home-page: https://github.com/pypa/sampleproject
Author: Edouard Yvinec
Author-email: Edouard Yvinec <ey@datakalab.com>
License: MIT License
Project-URL: documentation, https://www.ijcai.org/proceedings/2022/0223.pdf
Project-URL: repository, https://gitlab.com/ey_datakalab/batch-normalization-folding
Classifier: Programming Language :: Python :: 3
Classifier: License :: OSI Approved :: MIT License
Classifier: Operating System :: OS Independent
Requires-Python: >=3.9
License-File: LICENSE
Requires-Dist: tensorflow >=2.13.0
Requires-Dist: scikit-network >=0.31.0
